odoo/addons/mail_server_by_user/README.rst
odoo/addons/mail_server_by_user/__init__.py
odoo/addons/mail_server_by_user/__manifest__.py
odoo/addons/mail_server_by_user/i18n/es.po
odoo/addons/mail_server_by_user/i18n/fr.po
odoo/addons/mail_server_by_user/i18n/it.po
odoo/addons/mail_server_by_user/i18n/mail_server_by_user.pot
odoo/addons/mail_server_by_user/models/__init__.py
odoo/addons/mail_server_by_user/models/ir_mail_server.py
odoo/addons/mail_server_by_user/models/mail_mail.py
odoo/addons/mail_server_by_user/models/mail_thread.py
odoo/addons/mail_server_by_user/readme/CONTRIBUTORS.rst
odoo/addons/mail_server_by_user/readme/DESCRIPTION.rst
odoo/addons/mail_server_by_user/static/description/icon.png
odoo/addons/mail_server_by_user/static/description/index.html
odoo/addons/mail_server_by_user/tests/__init__.py
odoo/addons/mail_server_by_user/tests/test.msg
odoo/addons/mail_server_by_user/tests/test_mail_server_by_user.py
odoo14_addon_mail_server_by_user-14.0.1.0.1.dev13.dist-info/METADATA
odoo14_addon_mail_server_by_user-14.0.1.0.1.dev13.dist-info/WHEEL
odoo14_addon_mail_server_by_user-14.0.1.0.1.dev13.dist-info/top_level.txt
odoo14_addon_mail_server_by_user-14.0.1.0.1.dev13.dist-info/RECORD
